boela/__init__.py
boela/_utils.py
boela/constants.py
boela/ela/__init__.py
boela/ela/flacco.py
boela/ela/vm_features.py
boela/ela/vm_triples.py
boela/log.py
boela/model.py
boela/optimizer.py
boela/predictor.py
boela/problems/__init__.py
boela/problems/bbob/__init__.py
boela/problems/bbob/_problem.py
boela/problems/bbob/attractive_sector.py
boela/problems/bbob/bent_cigar.py
boela/problems/bbob/bueche_rastrigin.py
boela/problems/bbob/different_powers.py
boela/problems/bbob/discus.py
boela/problems/bbob/ellipsoid.py
boela/problems/bbob/ellipsoid_rotated.py
boela/problems/bbob/gallagher101.py
boela/problems/bbob/gallagher21.py
boela/problems/bbob/griewank_rosenbrock.py
boela/problems/bbob/katsuura.py
boela/problems/bbob/linear_slope.py
boela/problems/bbob/lunacek_bi_rastrigin.py
boela/problems/bbob/rastrigin.py
boela/problems/bbob/rastrigin_rotated.py
boela/problems/bbob/rosenbrock.py
boela/problems/bbob/rosenbrock_rotated.py
boela/problems/bbob/schaffers10.py
boela/problems/bbob/schaffers1000.py
boela/problems/bbob/schwefel.py
boela/problems/bbob/sharp_ridge.py
boela/problems/bbob/sphere.py
boela/problems/bbob/step_ellipsoid.py
boela/problems/bbob/weierstrass.py
boela/problems/doe.py
boela/problems/f1/__init__.py
boela/problems/f1/ackley.py
boela/problems/f1/amgm.py
boela/problems/f1/beale.py
boela/problems/f1/bohachevsky.py
boela/problems/f1/branin.py
boela/problems/f1/brent.py
boela/problems/f1/brown.py
boela/problems/f1/bukin02.py
boela/problems/f1/bukin04.py
boela/problems/f1/bukin06.py
boela/problems/f1/cigar.py
boela/problems/f1/csendes.py
boela/problems/f1/cube.py
boela/problems/f1/decanomial.py
boela/problems/f1/deceptive.py
boela/problems/f1/deckkersaarts.py
boela/problems/f1/dixonprice.py
boela/problems/f1/easom.py
boela/problems/f1/elatar.py
boela/problems/f1/ellipsoid.py
boela/problems/f1/exp2.py
boela/problems/f1/exponential.py
boela/problems/f1/goldsteinprice.py
boela/problems/f1/griewank.py
boela/problems/f1/gulf.py
boela/problems/f1/himmelblau.py
boela-0.1.3.dist-info/LICENSE
boela-0.1.3.dist-info/METADATA
boela-0.1.3.dist-info/WHEEL
boela-0.1.3.dist-info/RECORD
