Metadata-Version: 2.1
Name: boela
Version: 0.1.3
Summary: Bayesian Optimization with Exploratory Landscape Analysis
Home-page: https://github.com/agataleh/boela
License: MIT
Author: Taleh A. Agasiev
Author-email: tallex13@gmail.com
Requires-Python: >=3.11,<3.12
Classifier: License :: OSI Approved :: MIT License
Classifier: Programming Language :: Python :: 3
Classifier: Programming Language :: Python :: 3.11
Requires-Dist: bayesian-optimization (>=1.4.3,<2.0.0)
Requires-Dist: ioh (>=0.3.14,<0.4.0)
Requires-Dist: matplotlib (>=3.8.2,<4.0.0)
Requires-Dist: numpy (>=1.24.4,<2.0.0)
Requires-Dist: pflacco (>=1.2.2,<2.0.0)
